viz/__init__.py
viz/account.py
viz/amount.py
viz/block.py
viz/blockchain.py
viz/blockchainobject.py
viz/converter.py
viz/exceptions.py
viz/instance.py
viz/memo.py
viz/storage.py
viz/transactionbuilder.py
viz/utils.py
viz/viz.py
viz/wallet.py
viz/witness.py
vizapi/__init__.py
vizapi/consts.py
vizapi/exceptions.py
vizapi/noderpc.py
vizbase/__init__.py
vizbase/account.py
vizbase/chains.py
vizbase/exceptions.py
vizbase/memo.py
vizbase/objects.py
vizbase/operationids.py
vizbase/operations.py
vizbase/signedtransactions.py
viz_python_lib-1.0.2.dist-info/LICENSE.txt
viz_python_lib-1.0.2.dist-info/METADATA
viz_python_lib-1.0.2.dist-info/WHEEL
viz_python_lib-1.0.2.dist-info/RECORD
