Metadata-Version: 2.1
Name: viz-python-lib
Version: 1.0.2
Summary: Python library for VIZ blockchain
Home-page: https://github.com/VIZ-Blockchain/viz-python-lib
License: MIT
Keywords: viz,python,library,blockchain
Author: Vladimir Kamarzin
Author-email: vvk@vvk.pp.ru
Requires-Python: >=3.8,<4.0
Classifier: Development Status :: 3 - Alpha
Classifier: Intended Audience :: Developers
Classifier: License :: OSI Approved :: MIT License
Classifier: Operating System :: OS Independent
Classifier: Programming Language :: Python :: 3
Classifier: Programming Language :: Python :: 3.8
Classifier: Programming Language :: Python :: 3.9
Classifier: Programming Language :: Python :: 3.10
Classifier: Programming Language :: Python :: 3.11
Classifier: Programming Language :: Python :: 3.12
Classifier: Topic :: Software Development :: Libraries :: Python Modules
Requires-Dist: aiohttp (>=3.9.0b0) ; python_version >= "3.12"
Requires-Dist: docker (>=6.1.3,<7.0.0)
Requires-Dist: funcy (>=2.0,<3.0)
Requires-Dist: graphenelib (>=1.6.0,<2.0.0)
Requires-Dist: toolz (>=0.12.0,<0.13.0)
Project-URL: Repository, https://github.com/VIZ-Blockchain/viz-python-lib
